WatsonExplorer/__init__.py
WatsonExplorer/localhost.py
WatsonExplorer-2.0.1.dist-info/LICENSE
WatsonExplorer-2.0.1.dist-info/METADATA
WatsonExplorer-2.0.1.dist-info/WHEEL
WatsonExplorer-2.0.1.dist-info/top_level.txt
WatsonExplorer-2.0.1.dist-info/RECORD
