Metadata-Version: 2.1
Name: WatsonExplorer
Version: 2.0.1
Summary: Look into the data of your DataFrames with Watson Explorer
Author-email: HeintjeB <heinburgmans@gmail.com>
Project-URL: Repository, https://github.com/HeintjeB/watson
Project-URL: BugTracker, https://github.com/HeintjeB/watson/issues
Project-URL: Homepage, https://cobra-ms.com
Project-URL: Changelog, https://github.com/HeintjeB/watson/blob/main/CHANGELOG.md
Keywords: pandas,polars,explorer,watson
Classifier: Programming Language :: Python :: 3
Classifier: License :: OSI Approved :: MIT License
Classifier: Operating System :: OS Independent
Requires-Python: >=3.8
License-File: LICENSE
Requires-Dist: pandas ==2.1.4
Requires-Dist: polars ==0.20.3
